rhksm4/__init__.py
rhksm4/_methods.py
rhksm4/_sm4.py
rhksm4/_version.py
rhksm4-0.3.5.dist-info/LICENSE
rhksm4-0.3.5.dist-info/METADATA
rhksm4-0.3.5.dist-info/WHEEL
rhksm4-0.3.5.dist-info/top_level.txt
rhksm4-0.3.5.dist-info/RECORD
