Metadata-Version: 2.1
Name: rhksm4
Version: 0.3.5
Summary: A python package to read and parse .sm4 files from RHK Technology.
Home-page: https://gitlab.com/rhksm4/rhksm4
Author: Mirco Panighel
Author-email: panighel@iom.cnr.it
License: MIT
Platform: UNKNOWN
Classifier: Development Status :: 2 - Pre-Alpha
Classifier: Intended Audience :: Developers
Classifier: Natural Language :: English
Classifier: Programming Language :: Python :: 3
Classifier: License :: OSI Approved :: MIT License
Classifier: Operating System :: OS Independent
Requires-Python: >=3
Requires-Dist: numpy
